Metadata-Version: 2.1
Name: png2svglinlin
Version: 1.0.0
Summary: A library to convert PNG images to SVG format
Home-page: https://github.com/mialinlinlu/png2svgl3
Author: Linlin Lu
Author-email: linlinlu13@gmail.com
Classifier: Development Status :: 5 - Production/Stable
Classifier: Intended Audience :: Developers
Classifier: License :: OSI Approved :: MIT License
Classifier: Programming Language :: Python :: 3
Classifier: Programming Language :: Python :: 3.6
Classifier: Programming Language :: Python :: 3.7
Classifier: Programming Language :: Python :: 3.8
Classifier: Programming Language :: Python :: 3.9
License-File: LICENSE.txt
